LICENSE.txt
README.rst
setup.cfg
setup.py
lona_django/__init__.py
lona_django/forms.py
lona_django/middlewares.py
lona_django.egg-info/PKG-INFO
lona_django.egg-info/SOURCES.txt
lona_django.egg-info/dependency_links.txt
lona_django.egg-info/top_level.txt