Metadata-Version: 1.1
Name: lona-django
Version: 0.1.1
Summary: Django helper for Lona
Home-page: https://github.com/lona-web-org/lona-django
Author: Florian Scherf
Author-email: f.scherf@pengutronix.de
License: MIT
Platform: UNKNOWN
Classifier: License :: OSI Approved :: MIT License
